pend/__init__.py
pend/__version__.py
pend-1.0.2.dist-info/METADATA
pend-1.0.2.dist-info/WHEEL
pend-1.0.2.dist-info/top_level.txt
pend-1.0.2.dist-info/RECORD
