Metadata-Version: 2.1
Name: pend
Version: 1.0.2
Summary: Pendulum wrapper for short name.
Home-page: https://github.com/joyongjin/pend
Author: Jo Yongjin
Author-email: wnrhd114@gmail.com
License: MIT
Platform: UNKNOWN
Requires-Dist: pendulum
